azure/ai/agentshosting/__init__.py
azure/ai/agentshosting/_version.py
azure/ai/agentshosting/constants.py
azure/ai/agentshosting/logger.py
azure/ai/agentshosting/models/__init__.py
azure/ai/agentshosting/models/agents/__init__.py
azure/ai/agentshosting/models/agents/_client.py
azure/ai/agentshosting/models/agents/_configuration.py
azure/ai/agentshosting/models/agents/_patch.py
azure/ai/agentshosting/models/agents/_types.py
azure/ai/agentshosting/models/agents/_version.py
azure/ai/agentshosting/models/agents/py.typed
azure/ai/agentshosting/models/agents/_utils/__init__.py
azure/ai/agentshosting/models/agents/_utils/model_base.py
azure/ai/agentshosting/models/agents/_utils/serialization.py
azure/ai/agentshosting/models/agents/_utils/utils.py
azure/ai/agentshosting/models/agents/aio/__init__.py
azure/ai/agentshosting/models/agents/aio/_client.py
azure/ai/agentshosting/models/agents/aio/_configuration.py
azure/ai/agentshosting/models/agents/aio/_patch.py
azure/ai/agentshosting/models/agents/aio/operations/__init__.py
azure/ai/agentshosting/models/agents/aio/operations/_operations.py
azure/ai/agentshosting/models/agents/aio/operations/_patch.py
azure/ai/agentshosting/models/agents/models/__init__.py
azure/ai/agentshosting/models/agents/models/_enums.py
azure/ai/agentshosting/models/agents/models/_models.py
azure/ai/agentshosting/models/agents/models/_patch.py
azure/ai/agentshosting/models/agents/operations/__init__.py
azure/ai/agentshosting/models/agents/operations/_operations.py
azure/ai/agentshosting/models/agents/operations/_patch.py
azure/ai/agentshosting/models/openai/__init__.py
azure/ai/agentshosting/models/openai/models/__init__.py
azure/ai/agentshosting/models/openai/models/_enums.py
azure/ai/agentshosting/models/openai/models/_models.py
azure/ai/agentshosting/models/openai/models/_patch.py
azure/ai/agentshosting/server/__init__.py
azure/ai/agentshosting/server/agent_framework.py
azure/ai/agentshosting/server/base.py
azure/ai/agentshosting/server/langgraph.py
my_agents_adapter-0.0.8.dist-info/METADATA
my_agents_adapter-0.0.8.dist-info/WHEEL
my_agents_adapter-0.0.8.dist-info/top_level.txt
my_agents_adapter-0.0.8.dist-info/RECORD
