Metadata-Version: 2.4
Name: my-agents-adapter
Version: 0.0.8
Summary: Agents hosting adapter for Azure AI
Author: Microsoft Corporation
Classifier: Programming Language :: Python :: 3
Classifier: Programming Language :: Python :: 3.10
Requires-Python: >=3.10
Requires-Dist: azure-monitor-opentelemetry
Requires-Dist: azure-ai-projects
Requires-Dist: azure-ai-agents>=1.2.0b5
Requires-Dist: azure-identity
Requires-Dist: opentelemetry-api
Requires-Dist: starlette
Requires-Dist: uvicorn
Provides-Extra: agentframework
Requires-Dist: agent_framework_azure_ai==1.0.0b251007; extra == "agentframework"
Requires-Dist: opentelemetry-exporter-otlp-proto-grpc; extra == "agentframework"
Provides-Extra: langgraph
Requires-Dist: langchain; extra == "langgraph"
Requires-Dist: langchain-openai; extra == "langgraph"
Requires-Dist: langchain-azure-ai[opentelemetry]; extra == "langgraph"
Requires-Dist: langgraph; extra == "langgraph"
Requires-Dist: opentelemetry-exporter-otlp-proto-http; extra == "langgraph"
